meteofetch/__init__.py
meteofetch/_misc.py
meteofetch/_model.py
meteofetch/_ww3.py
meteofetch/ecmwf/__init__.py
meteofetch/ecmwf/aifs.py
meteofetch/ecmwf/ifs.py
meteofetch/gribdefs/grib2/shortName.def
meteofetch/gribdefs/grib2/localConcepts/lfpw/shortName.def
meteofetch/gribdefs/grib2/tables/15/4.5.table
meteofetch/meteofrance/__init__.py
meteofetch/meteofrance/arome.py
meteofetch/meteofrance/arpege.py
meteofetch/meteofrance/mfwam.py
meteofetch-0.5.6.dist-info/METADATA
meteofetch-0.5.6.dist-info/WHEEL
meteofetch-0.5.6.dist-info/licenses/LICENSE
meteofetch-0.5.6.dist-info/RECORD
