Metadata-Version: 2.4
Name: meteofetch
Version: 0.5.6
Summary: Package python pour récupérer les données modélisées de prévision de MétéoFrance et de l'ECMWF
Project-URL: Homepage, https://github.com/CyrilJl/meteofetch
Project-URL: Documentation, https://meteofetch.readthedocs.io
Author: Cyril Joly
License-File: LICENSE
Classifier: License :: OSI Approved :: MIT License
Classifier: Operating System :: OS Independent
Classifier: Programming Language :: Python :: 3
Requires-Python: >=3.8
Requires-Dist: cfgrib
Requires-Dist: requests
Requires-Dist: xarray
Provides-Extra: test
Requires-Dist: pytest; extra == 'test'
